pojediga/__init__.py
pojediga/pojediga.py
pojediga-3.3.3.dist-info/METADATA
pojediga-3.3.3.dist-info/WHEEL
pojediga-3.3.3.dist-info/top_level.txt
pojediga-3.3.3.dist-info/RECORD
