Metadata-Version: 2.1
Name: pojediga
Version: 3.3.3
Summary: A simple pojediga package to feel good every day, every night
Author: 🇷🇸
Author-email: ja_sam_lekar_za_sve@pojediga.rs
Classifier: Programming Language :: Python :: 3
Classifier: License :: OSI Approved :: MIT License
Classifier: Operating System :: OS Independent
Requires-Python: >=3.9
